unicorncommon/__init__.py
unicorncommon/dbagent_client.py
unicorncommon/newkey.py
unicorncommon/server_status.py
unicorncommon/channels/__init__.py
unicorncommon/channels/bucket.py
unicorncommon/channels/tcp.py
unicorncommon/pmonitor/__init__.py
unicorncommon/pmonitor/pmonitor.py
unicorncommon/pmonitor/pwrapper.py
unicorncommon/pmonitor/pmonitor_impl/__init__.py
unicorncommon/pmonitor/pmonitor_impl/api_input.py
unicorncommon/pmonitor/pmonitor_impl/executor.py
unicorncommon/pmonitor/pmonitor_impl/main.py
unicorncommon-0.0.29.dist-info/METADATA
unicorncommon-0.0.29.dist-info/WHEEL
unicorncommon-0.0.29.dist-info/entry_points.txt
unicorncommon-0.0.29.dist-info/top_level.txt
unicorncommon-0.0.29.dist-info/RECORD
