Metadata-Version: 2.1
Name: unicorncommon
Version: 0.0.29
Summary: Common Libraries for Unicorn Cluster Manager
Home-page: https://github.com/stonezhong/unicorn/tree/main/common
Author: Stone Zhong
Author-email: stonezhong@hotmail.com
License: MIT
Platform: UNKNOWN
Classifier: License :: OSI Approved :: MIT License
Classifier: Programming Language :: Python :: 3
Requires-Dist: pyappkit
Requires-Dist: jsonschema
Requires-Dist: python-dateutil
Requires-Dist: pyzmq
Requires-Dist: PyYAML
